{"scraped":[2889720,2889779,2921156,2921159,2953846,2953853,2988250,3047395,3725605,3088763],"lastrun":{"sundowns":"2017-08-16","curtinsmash":"2017-08-16","perthsmash":"2012-08-16"},"records":[{"id":2889720,"name":"Sector Z 11: Melee Singles (Quasi-Arcadian Edition)","startDate":"2016-10-03T05:16:13.574-06:00","endDate":"2016-10-03T09:07:48.488-06:00","participants":22,"owner":"curtinsmash","matchesScraped":1},{"id":2889779,"name":"Sector Z 11: Redemption","startDate":"2016-10-03T06:18:40.514-06:00","endDate":"2016-10-03T07:52:20.109-06:00","participants":11,"owner":"curtinsmash","matchesScraped":1},{"id":2921156,"name":"Sector Z 12: Melee Singles","startDate":"2016-10-17T05:20:17.627-06:00","endDate":"2016-10-17T08:39:20.073-06:00","participants":27,"owner":"curtinsmash","matchesScraped":1},{"id":2921159,"name":"Sector Z 12: Melee Redemption Bracket","startDate":"2016-10-17T06:27:15.883-06:00","endDate":"2016-10-17T08:38:49.637-06:00","participants":12,"owner":"curtinsmash","matchesScraped":1},{"id":2953846,"name":"Sector Z 13: Melee Singles","startDate":"2016-10-31T05:15:39.465-06:00","endDate":"2016-10-31T08:15:25.187-06:00","participants":14,"owner":"curtinsmash","matchesScraped":1},{"id":2953853,"name":"Sector Z 13: Melee Redemption","startDate":"2016-10-31T06:39:10.236-06:00","endDate":"2016-10-31T08:41:50.816-06:00","participants":6,"owner":"curtinsmash","matchesScraped":1},{"id":2988250,"name":"Sector Z 14: Melee Singles","startDate":"2016-11-14T04:30:45.078-07:00","endDate":"2016-11-14T07:53:49.563-07:00","participants":16,"owner":"curtinsmash","matchesScraped":1},{"id":3047395,"name":"Sector Z 15 Melee Singles","startDate":"2016-12-09T23:47:40.395-07:00","endDate":"2016-12-10T00:44:28.301-07:00","participants":8,"owner":"curtinsmash","matchesScraped":1},{"id":3725605,"name":"Sector Z 16: A Melee Fortnightly ","startDate":"2017-08-07T05:37:35.667-06:00","endDate":"2017-08-07T08:47:55.150-06:00","participants":17,"owner":"curtinsmash","matchesScraped":1},{"id":3088763,"name":"Smash @ Sunny's 3.0","startDate":"2016-12-28T09:27:41.083+00:00","endDate":"2016-12-28T14:37:55.032+00:00","participants":14,"owner":"sundowns","matchesScraped":1}]}
